odoo/addons/website_sale_cart_no_redirect/README.rst
odoo/addons/website_sale_cart_no_redirect/__init__.py
odoo/addons/website_sale_cart_no_redirect/__manifest__.py
odoo/addons/website_sale_cart_no_redirect/i18n/website_sale_cart_no_redirect.pot
odoo/addons/website_sale_cart_no_redirect/models/__init__.py
odoo/addons/website_sale_cart_no_redirect/models/res_config_settings.py
odoo/addons/website_sale_cart_no_redirect/models/website.py
odoo/addons/website_sale_cart_no_redirect/readme/CONFIGURE.rst
odoo/addons/website_sale_cart_no_redirect/readme/CONTRIBUTORS.rst
odoo/addons/website_sale_cart_no_redirect/readme/DESCRIPTION.rst
odoo/addons/website_sale_cart_no_redirect/readme/HISTORY.rst
odoo/addons/website_sale_cart_no_redirect/readme/ROADMAP.rst
odoo/addons/website_sale_cart_no_redirect/static/description/icon.png
odoo/addons/website_sale_cart_no_redirect/static/description/index.html
odoo/addons/website_sale_cart_no_redirect/static/src/js/website_sale_cart_no_redirect.js
odoo/addons/website_sale_cart_no_redirect/static/src/js/website_utils.js
odoo/addons/website_sale_cart_no_redirect/static/src/js/tours/add_to_cart_no_redirect.js
odoo/addons/website_sale_cart_no_redirect/static/src/js/tours/add_to_cart_redirect.js
odoo/addons/website_sale_cart_no_redirect/templates/templates.xml
odoo/addons/website_sale_cart_no_redirect/tests/__init__.py
odoo/addons/website_sale_cart_no_redirect/tests/test_ui.py
odoo/addons/website_sale_cart_no_redirect/views/assets.xml
odoo/addons/website_sale_cart_no_redirect/views/res_config_settings_views.xml
odoo13_addon_website_sale_cart_no_redirect-13.0.1.0.1.dev5.dist-info/METADATA
odoo13_addon_website_sale_cart_no_redirect-13.0.1.0.1.dev5.dist-info/WHEEL
odoo13_addon_website_sale_cart_no_redirect-13.0.1.0.1.dev5.dist-info/top_level.txt
odoo13_addon_website_sale_cart_no_redirect-13.0.1.0.1.dev5.dist-info/RECORD
